CHANGELOG.md
flowchart_explorer/__init__.py
flowchart_explorer/chartpath.py
flowchart_explorer/explorer.py
flowchart_explorer/flowchartdiagrams/__init__.py
flowchart_explorer/flowchartdiagrams/nodes.py
flowchart_explorer/graph/__init__.py
flowchart_explorer/graph/drawio.py
flowchart_explorer/methods.py
flowchart_explorer-0.1.2.dist-info/LICENSE
flowchart_explorer-0.1.2.dist-info/METADATA
flowchart_explorer-0.1.2.dist-info/WHEEL
flowchart_explorer-0.1.2.dist-info/RECORD
